aspose/__init__.py
aspose/asposeocr.so
aspose/doc/apireference.url
aspose/doc/python-cpp-doc.url
aspose/license/Aspose_End-User-License-Agreement.txt
aspose/license/End User License Agreement.html
aspose_ocr_python_cpp-25.2.0.dist-info/LICENSE
aspose_ocr_python_cpp-25.2.0.dist-info/METADATA
aspose_ocr_python_cpp-25.2.0.dist-info/WHEEL
aspose_ocr_python_cpp-25.2.0.dist-info/top_level.txt
aspose_ocr_python_cpp-25.2.0.dist-info/RECORD
